{
  "config": "{\"version\":\"5.27\",\"themeCollection\":{\"baseTheme\":{\"name\":\"CY21SU11\",\"version\":\"5.28\",\"type\":2}},\"activeSectionIndex\":0,\"defaultDrillFilterOtherVisuals\":true,\"linguisticSchemaSyncVersion\":2,\"settings\":{\"useNewFilterPaneExperience\":true,\"allowChangeFilterTypes\":true,\"useStylableVisualContainerHeader\":true,\"exportDataMode\":1},\"objects\":{\"section\":[{\"properties\":{\"verticalAlignment\":{\"expr\":{\"Literal\":{\"Value\":\"'Top'\"}}}}}]}}",
  "filters": "[]",
  "layoutOptimization": 0,
  "resourcePackages": [
    {
      "resourcePackage": {
        "disabled": false,
        "items": [
          {
            "name": "CY21SU11",
            "path": "BaseThemes/CY21SU11.json",
            "type": 202
          }
        ],
        "name": "SharedResources",
        "type": 2
      }
    }
  ],
  "sections": [
    {
      "config": "{}",
      "displayName": "Page 1",
      "displayOption": 1,
      "filters": "[{\"name\":\"Filterd9e0e8401dc9ced5261a\",\"expression\":{\"Column\":{\"Expression\":{\"SourceRef\":{\"Entity\":\"DIm - Task Date\"}},\"Property\":\"Task Year\"}},\"type\":\"Categorical\",\"howCreated\":1,\"objects\":{\"general\":[{\"properties\":{\"isInvertedSelectionMode\":{\"expr\":{\"Literal\":{\"Value\":\"true\"}}}}}]}}]",
      "height": 720.00,
      "name": "ReportSection",
      "visualContainers": [
        {
          "config": "{\"name\":\"b862350a76eb31021c50\",\"layouts\":[{\"id\":0,\"position\":{\"x\":9.72644376899696,\"y\":0,\"z\":0,\"width\":1270.273556231003,\"height\":592.3404255319149}}],\"singleVisual\":{\"visualType\":\"tableEx\",\"projections\":{\"Values\":[{\"queryRef\":\"Sum(Facts - QA Utilization.Task Total Hours)\"},{\"queryRef\":\"Sum(Facts - QA Utilization.Timesheet Total Hours)\"},{\"queryRef\":\"Dim - Employee.Employee COU\"},{\"queryRef\":\"Dim - Employee.Employee Sub Unit\"},{\"queryRef\":\"Dim - Employee.Employee Number\"},{\"queryRef\":\"Facts - QA Utilization.Task Date\"},{\"queryRef\":\"Facts - QA Utilization.Timesheet Approved Date\"},{\"queryRef\":\"Facts - QA Utilization.Timesheet Start Date\"},{\"queryRef\":\"Facts - QA Utilization.Timesheet End Date\"}]},\"prototypeQuery\":{\"Version\":2,\"From\":[{\"Name\":\"f\",\"Entity\":\"Facts - QA Utilization\",\"Type\":0},{\"Name\":\"d\",\"Entity\":\"Dim - Employee\",\"Type\":0}],\"Select\":[{\"Aggregation\":{\"Expression\":{\"Column\":{\"Expression\":{\"SourceRef\":{\"Source\":\"f\"}},\"Property\":\"Task Total Hours\"}},\"Function\":0},\"Name\":\"Sum(Facts - QA Utilization.Task Total Hours)\"},{\"Aggregation\":{\"Expression\":{\"Column\":{\"Expression\":{\"SourceRef\":{\"Source\":\"f\"}},\"Property\":\"Timesheet Total Hours\"}},\"Function\":0},\"Name\":\"Sum(Facts - QA Utilization.Timesheet Total Hours)\"},{\"Column\":{\"Expression\":{\"SourceRef\":{\"Source\":\"d\"}},\"Property\":\"Employee COU\"},\"Name\":\"Dim - Employee.Employee COU\"},{\"Column\":{\"Expression\":{\"SourceRef\":{\"Source\":\"d\"}},\"Property\":\"Employee Sub Unit\"},\"Name\":\"Dim - Employee.Employee Sub Unit\"},{\"Column\":{\"Expression\":{\"SourceRef\":{\"Source\":\"d\"}},\"Property\":\"Employee Number\"},\"Name\":\"Dim - Employee.Employee Number\"},{\"Column\":{\"Expression\":{\"SourceRef\":{\"Source\":\"f\"}},\"Property\":\"Task Date\"},\"Name\":\"Facts - QA Utilization.Task Date\"},{\"Column\":{\"Expression\":{\"SourceRef\":{\"Source\":\"f\"}},\"Property\":\"Timesheet Approved Date\"},\"Name\":\"Facts - QA Utilization.Timesheet Approved Date\"},{\"Column\":{\"Expression\":{\"SourceRef\":{\"Source\":\"f\"}},\"Property\":\"Timesheet Start Date\"},\"Name\":\"Facts - QA Utilization.Timesheet Start Date\"},{\"Column\":{\"Expression\":{\"SourceRef\":{\"Source\":\"f\"}},\"Property\":\"Timesheet End Date\"},\"Name\":\"Facts - QA Utilization.Timesheet End Date\"}]},\"drillFilterOtherVisuals\":true,\"filterSortOrder\":3}}",
          "filters": "[{\"name\":\"Filter45243dfe5bde5ed94582\",\"expression\":{\"Column\":{\"Expression\":{\"SourceRef\":{\"Entity\":\"Dim - Employee\"}},\"Property\":\"Employee COU\"}},\"type\":\"Categorical\",\"howCreated\":0,\"isHiddenInViewMode\":false,\"ordinal\":0},{\"name\":\"Filterd9a5ea020e816cd4e7a5\",\"expression\":{\"Column\":{\"Expression\":{\"SourceRef\":{\"Entity\":\"Dim - Employee\"}},\"Property\":\"Employee Number\"}},\"type\":\"Categorical\",\"howCreated\":0,\"isHiddenInViewMode\":false,\"ordinal\":1},{\"name\":\"Filter7e9281e208b31980b354\",\"expression\":{\"Column\":{\"Expression\":{\"SourceRef\":{\"Entity\":\"Dim - Employee\"}},\"Property\":\"Employee Sub Unit\"}},\"type\":\"Categorical\",\"howCreated\":0,\"isHiddenInViewMode\":false,\"ordinal\":2},{\"name\":\"Filter7bbf8b83393a1cdc0798\",\"expression\":{\"Column\":{\"Expression\":{\"SourceRef\":{\"Entity\":\"Facts - QA Utilization\"}},\"Property\":\"Task Date\"}},\"type\":\"Categorical\",\"howCreated\":0,\"isHiddenInViewMode\":false,\"ordinal\":3},{\"name\":\"Filter8e4bea1679984110c6c5\",\"expression\":{\"Aggregation\":{\"Expression\":{\"Column\":{\"Expression\":{\"SourceRef\":{\"Entity\":\"Facts - QA Utilization\"}},\"Property\":\"Task Total Hours\"}},\"Function\":0}},\"type\":\"Advanced\",\"howCreated\":0,\"isHiddenInViewMode\":false,\"ordinal\":4},{\"name\":\"Filter96309a42272805ab11be\",\"expression\":{\"Column\":{\"Expression\":{\"SourceRef\":{\"Entity\":\"Facts - QA Utilization\"}},\"Property\":\"Timesheet Approved Date\"}},\"type\":\"Categorical\",\"howCreated\":0,\"isHiddenInViewMode\":false,\"ordinal\":5},{\"name\":\"Filter47eec767dd2e8b8d40e3\",\"expression\":{\"Column\":{\"Expression\":{\"SourceRef\":{\"Entity\":\"Facts - QA Utilization\"}},\"Property\":\"Timesheet End Date\"}},\"type\":\"Categorical\",\"howCreated\":0,\"isHiddenInViewMode\":false,\"ordinal\":6},{\"name\":\"Filter8cca5ae0abec594687a6\",\"expression\":{\"Column\":{\"Expression\":{\"SourceRef\":{\"Entity\":\"Facts - QA Utilization\"}},\"Property\":\"Timesheet Start Date\"}},\"type\":\"Categorical\",\"howCreated\":0,\"isHiddenInViewMode\":false,\"ordinal\":7},{\"name\":\"Filterb3cbcd98896cda4c38b0\",\"expression\":{\"Aggregation\":{\"Expression\":{\"Column\":{\"Expression\":{\"SourceRef\":{\"Entity\":\"Facts - QA Utilization\"}},\"Property\":\"Timesheet Total Hours\"}},\"Function\":0}},\"type\":\"Advanced\",\"howCreated\":0,\"isHiddenInViewMode\":false,\"ordinal\":8}]",
          "height": 592.34,
          "width": 1270.27,
          "x": 9.72,
          "y": 0.00,
          "z": 0.00
        }
      ],
      "width": 1280.00
    }
  ]
}